config.py
pychange/__init__.py
pychange/pychange.py
pychange/pyload.py
pychange.egg-info/PKG-INFO
pychange.egg-info/SOURCES.txt
pychange.egg-info/dependency_links.txt
pychange.egg-info/top_level.txt