Metadata-Version: 2.1
Name: pychange
Version: 0.0.1
Summary: to change a string to a dict or a list
Home-page: UNKNOWN
Author: XuYang Zhu
Author-email: zhuxuyangdudunj@icloud.com
License: Apache License
Platform: any
